setup.py
distributions_from_mercy2/Binomialdistribution.py
distributions_from_mercy2/Gaussiandistribution.py
distributions_from_mercy2/Generaldistribution.py
distributions_from_mercy2/__init__.py
distributions_from_mercy2.egg-info/PKG-INFO
distributions_from_mercy2.egg-info/SOURCES.txt
distributions_from_mercy2.egg-info/dependency_links.txt
distributions_from_mercy2.egg-info/not-zip-safe
distributions_from_mercy2.egg-info/top_level.txt