Metadata-Version: 2.1
Name: distributions-from-mercy2
Version: 0.1
Summary: Gaussian distributions
Home-page: UNKNOWN
License: UNKNOWN
Platform: UNKNOWN
